aws_dataclasses/__init__.py
aws_dataclasses/alexa_skill_event.py
aws_dataclasses/base.py
aws_dataclasses/cf_event.py
aws_dataclasses/cloudwatch_alarm.py
aws_dataclasses/cloudwatch_event.py
aws_dataclasses/http_proxy_event.py
aws_dataclasses/lambda_function_configuration.py
aws_dataclasses/s3_event.py
aws_dataclasses/sns_event.py
python_aws_dataclasses-0.4.5.dist-info/LICENSE
python_aws_dataclasses-0.4.5.dist-info/WHEEL
python_aws_dataclasses-0.4.5.dist-info/METADATA
python_aws_dataclasses-0.4.5.dist-info/RECORD
