Metadata-Version: 2.1
Name: python-aws-dataclasses
Version: 0.4.5
Summary: python-aws-dataclasses
Home-page: https://github.com/hypoport/python-aws-dataclasses
License: UNKNOWN
Keywords: aws lambda events
Author: Benjamin Weigel
Author-email: benjamin.weigel@europace.de
Requires-Python: >=3.6
Classifier: License :: OSI Approved :: Apache Software License
Classifier: Development Status :: 4 - Beta
Classifier: Intended Audience :: Developers
Classifier: Programming Language :: Python :: 3.6
Classifier: Programming Language :: Python :: 3.7
Requires-Dist: dataclasses>=0.6; python_version == '3.6'
Requires-Dist: arrow>=0.11.0
Requires-Dist: pytest >=2.7.3; extra == "test"
Requires-Dist: pytest-runner; extra == "test"
Requires-Dist: sphinx; extra == "doc"
Provides-Extra: .none
Provides-Extra: doc
Provides-Extra: test
